graphh/CGH.py
graphh/CGHError.py
graphh/__init__.py
graphh-0.1.3.dist-info/LICENSE
graphh-0.1.3.dist-info/METADATA
graphh-0.1.3.dist-info/WHEEL
graphh-0.1.3.dist-info/top_level.txt
graphh-0.1.3.dist-info/RECORD
