Metadata-Version: 2.1
Name: graphh
Version: 0.1.3
Summary: A module to make GraphHopper API queries easy
Home-page: https://github.com/chuuw/graphh/
Author: Maëlle Cosson, Pauline Hamon-Giraud, Clément Caillard and Romain Tavenard
Author-email: 
License: UNKNOWN
Platform: UNKNOWN
Classifier: Programming Language :: Python :: 3
Classifier: License :: OSI Approved :: BSD License
Classifier: Operating System :: OS Independent
